{
    "fields": [
        {
            "name": "Titre",
            "value": "Anges et Demons"
        },
        {
            "name": "Réalisateur(s)",
            "value": "Ron Howard"
        },
        {
            "name": "Genre",
            "value": "Action. Aventure. Policier et Thriller"
        },
        {
            "name": "Durée (min)",
            "value": ""
        },
        {
            "name": "Acteurs",
            "value": "Tom Hanks Ewan McGregor Stellan Skarsgard"
        },
        {
            "name": "Date de sortie (DVD)",
            "value": "31/12/2008"
        },
        {
            "name": "Date d'achat",
            "value": ""
        },
        {
            "name": "Classement",
            "value": "0 %"
        },
        {
            "name": "Zone",
            "value": "2"
        },
        {
            "name": "Code pegi",
            "value": ""
        },
        {
            "name": "Nombre de supports",
            "value": "1"
        },
        {
            "name": "Prix d'achat",
            "value": "0.00 €"
        },
        {
            "name": "Prêt",
            "value": ""
        },
        {
            "name": "Type de support",
            "value": "DVD"
        },
        {
            "name": "Etat",
            "value": ""
        },
        {
            "name": "Prix actuel",
            "value": ""
        },
        {
            "name": "Souhaité",
            "value": ""
        },
        {
            "name": "Synopsis",
            "value": "Lorsque Langdon met en evidence la resurgence d'une ancienne societe secrete (les Illuminati la plus puissante des organisations secretes de l'histoire de l'humanite) il met egalement a jour une menace mortelle pour l'existence de son ennemi jure : l'Eglise catholique. Lorsqu'il apprend que les Illuminati ont arme une ineluctable bombe a retardement Langdon se rend a Rome ou il s'allie a Vittoria Vetra une superbe et mysterieuse scientifique italienne. S'embarquant dans une chasse haletante et pleine d'action a travers des cryptes scellees des catacombes dangereuses des cathedrales desertees et meme le coffre-fort le plus secret du monde Langdon et Vetra suivront une piste remontant a 400 ans de symboles anciens qui constituent le seul espoir de survie du Vatican.}"
        },
        {
            "name": "Commentaires",
            "value": "A vendre Antoine"
        },
        {
            "name": "Autres infos",
            "value": ""
        },
        {
            "name": "Studio d'enregistrement",
            "value": "SONY PICTURES HOME ENTERTAINMENT"
        },
        {
            "name": "Pays",
            "value": ""
        },
        {
            "name": "Langue(s)",
            "value": ""
        },
        {
            "name": "Sous-titres",
            "value": ""
        },
        {
            "name": "Son",
            "value": ""
        },
        {
            "name": "Ratio",
            "value": "1.33:1"
        },
        {
            "name": "EAN",
            "value": "8712609659955"
        },
        {
            "name": "Format",
            "value": "PAL"
        },
        {
            "name": "Visionné",
            "value": ""
        },
        {
            "name": "Producteur",
            "value": ""
        },
        {
            "name": "Date de création",
            "value": "30/12/2017 10:27"
        },
        {
            "name": "Date de modification",
            "value": "02/09/2025 18:35"
        }
    ],
    "main_title": "Anges et Demons",
    "sub_title": "DVD",
    "thumbnail_big": "db/1187_video/thumbnail_big",
    "thumbnail_mini": "db/1187_video/thumbnail_small"
}
