{
    "fields": [
        {
            "name": "Série",
            "value": "One Piece"
        },
        {
            "name": "Titre",
            "value": "One Piece. Tome 09. Une jeune fille en pleurs"
        },
        {
            "name": "Scénario",
            "value": ""
        },
        {
            "name": "Editeur",
            "value": "Glenat"
        },
        {
            "name": "Dessins",
            "value": ""
        },
        {
            "name": "Langue",
            "value": ""
        },
        {
            "name": "Couleurs",
            "value": ""
        },
        {
            "name": "Nbre de pages",
            "value": ""
        },
        {
            "name": "Date de parution",
            "value": "19/02/2002"
        },
        {
            "name": "Dédicacé",
            "value": ""
        },
        {
            "name": "N°",
            "value": ""
        },
        {
            "name": "Genre ",
            "value": "Manga"
        },
        {
            "name": "Date d'achat",
            "value": ""
        },
        {
            "name": "Prix d'achat",
            "value": "6.90 €"
        },
        {
            "name": "Prêt",
            "value": ""
        },
        {
            "name": "Etat",
            "value": ""
        },
        {
            "name": "Classement",
            "value": "0 %"
        },
        {
            "name": "Prix actuel",
            "value": ""
        },
        {
            "name": "Souhaité",
            "value": ""
        },
        {
            "name": "Résumé",
            "value": ""
        },
        {
            "name": "Autres infos",
            "value": ""
        },
        {
            "name": "Format",
            "value": "PAL"
        },
        {
            "name": "Collection",
            "value": ""
        },
        {
            "name": "Style",
            "value": ""
        },
        {
            "name": "Pays",
            "value": ""
        },
        {
            "name": "Type d'édition",
            "value": ""
        },
        {
            "name": "Illustrateur",
            "value": ""
        },
        {
            "name": "EAN / ISBN",
            "value": "9782723436243"
        },
        {
            "name": "Imprimeur",
            "value": ""
        },
        {
            "name": "Achevé d'imprimer",
            "value": ""
        },
        {
            "name": "Dépôt légal",
            "value": ""
        },
        {
            "name": "Date de création",
            "value": "30/12/2017 16:56"
        },
        {
            "name": "Date de modification",
            "value": "17/02/2022 20:15"
        }
    ],
    "main_title": "One Piece",
    "sub_title": "One Piece. Tome 09. Une jeune fille en pleurs",
    "thumbnail_big": "db/884_comics/thumbnail_big",
    "thumbnail_mini": "db/884_comics/thumbnail_small"
}
