{
    "fields": [
        {
            "name": "Titre",
            "value": "Roi Arthur (Le) - Version Director's cut"
        },
        {
            "name": "Réalisateur(s)",
            "value": "Antoine Fuqua"
        },
        {
            "name": "Genre",
            "value": "Historique, Action"
        },
        {
            "name": "Durée (min)",
            "value": "126"
        },
        {
            "name": "Acteurs",
            "value": "Clive Owen Keira Knightley Ioan Gruffudd Stephen Dillane Stellan Skarsgard"
        },
        {
            "name": "Date de sortie (DVD)",
            "value": "04/08/2004"
        },
        {
            "name": "Date d'achat",
            "value": "25/11/2023"
        },
        {
            "name": "Classement",
            "value": "0 %"
        },
        {
            "name": "Zone",
            "value": "2"
        },
        {
            "name": "Code pegi",
            "value": "Tous publics"
        },
        {
            "name": "Nombre de supports",
            "value": "1"
        },
        {
            "name": "Prix d'achat",
            "value": "2.88 €"
        },
        {
            "name": "Prêt",
            "value": ""
        },
        {
            "name": "Type de support",
            "value": "Blu-Ray"
        },
        {
            "name": "Etat",
            "value": "Bon"
        },
        {
            "name": "Prix actuel",
            "value": ""
        },
        {
            "name": "Souhaité",
            "value": ""
        },
        {
            "name": "Synopsis",
            "value": "Après cinq siècles de domination sur la Grande-Bretagne, l'Empire romain, chaque jour plus affaibli, abandonne l'île pourtant menacée par les invasions sanguinaires des Saxons.\n\nAvant d'être libéré de ses obligations, Arthur se voit confier une dernière mission. Il doit secourir la belle Guenièvre, torturée pour hérésie. Avec ses chevaliers, il prend conscience qu'ils sont le dernier espoir face au massacre programmé par les Saxons.\n\nTandis que les chevaliers tentent de conduire le peuple et les nobles à l'abri du Mur d'Hadrien, Arthur doit choisir son destin. S'il s'enfuit, il sera libre ; s'il s'oppose aux légions de Saxons qui s'apprêtent à déferler, il sera certainement tué. Il ignore que sa décision changera le cours de l'Histoire. "
        },
        {
            "name": "Commentaires",
            "value": ""
        },
        {
            "name": "Autres infos",
            "value": ""
        },
        {
            "name": "Studio d'enregistrement",
            "value": "Buena Vista Home Entertainement"
        },
        {
            "name": "Pays",
            "value": ""
        },
        {
            "name": "Langue(s)",
            "value": ""
        },
        {
            "name": "Sous-titres",
            "value": ""
        },
        {
            "name": "Son",
            "value": ""
        },
        {
            "name": "Ratio",
            "value": "1.33:1"
        },
        {
            "name": "EAN",
            "value": "8717418120856"
        },
        {
            "name": "Format",
            "value": "PAL"
        },
        {
            "name": "Visionné",
            "value": ""
        },
        {
            "name": "Producteur",
            "value": ""
        },
        {
            "name": "Date de création",
            "value": "25/11/2023 22:40"
        },
        {
            "name": "Date de modification",
            "value": "25/11/2023 22:50"
        }
    ],
    "main_title": "Roi Arthur (Le) - Version Director's cut",
    "sub_title": "Blu-Ray",
    "thumbnail_big": "db/2321_video/thumbnail_big",
    "thumbnail_mini": "db/2321_video/thumbnail_small"
}
