{
    "fields": [
        {
            "name": "Titre",
            "value": "Dernier samourai (Le)"
        },
        {
            "name": "Réalisateur(s)",
            "value": "Edward Zwick"
        },
        {
            "name": "Genre",
            "value": "Historique, Guerre"
        },
        {
            "name": "Durée (min)",
            "value": ""
        },
        {
            "name": "Acteurs",
            "value": "Tom Cruise Billy Connolly Tony Goldwyn Timothy Spall Jiroyuki Sanada"
        },
        {
            "name": "Date de sortie (DVD)",
            "value": "14/01/2004"
        },
        {
            "name": "Date d'achat",
            "value": "30/08/2023"
        },
        {
            "name": "Classement",
            "value": "0 %"
        },
        {
            "name": "Zone",
            "value": "2"
        },
        {
            "name": "Code pegi",
            "value": ""
        },
        {
            "name": "Nombre de supports",
            "value": "1"
        },
        {
            "name": "Prix d'achat",
            "value": "2.99 €"
        },
        {
            "name": "Prêt",
            "value": ""
        },
        {
            "name": "Type de support",
            "value": "Blu-Ray"
        },
        {
            "name": "Etat",
            "value": "Bon"
        },
        {
            "name": "Prix actuel",
            "value": ""
        },
        {
            "name": "Souhaité",
            "value": ""
        },
        {
            "name": "Synopsis",
            "value": "Tom Cruise interprete le role du capitaine Nathan Algren un heros de la guerre de Secession qui voyage au Japon pour y combattre les Samouris mais se joint finalement a eux. Ken Watanabe nomine pour un Oscar joue le role de Katsumoto un des chefs des Samouris qui voit disparaitre peu a peu les traditions de son peuple et dont le destin se relie a celui du capitaine americain. Edward Zwick (laureat du Prix de la Meilleure Realisation decerne par le National Board of Review) est le realisateur de cette epopee entrainante et pleine d'emotions sur la naissance du Japon moderne.}"
        },
        {
            "name": "Commentaires",
            "value": ""
        },
        {
            "name": "Autres infos",
            "value": ""
        },
        {
            "name": "Studio d'enregistrement",
            "value": "_"
        },
        {
            "name": "Pays",
            "value": ""
        },
        {
            "name": "Langue(s)",
            "value": ""
        },
        {
            "name": "Sous-titres",
            "value": ""
        },
        {
            "name": "Son",
            "value": ""
        },
        {
            "name": "Ratio",
            "value": "1.33:1"
        },
        {
            "name": "EAN",
            "value": "7321910108093"
        },
        {
            "name": "Format",
            "value": "PAL"
        },
        {
            "name": "Visionné",
            "value": ""
        },
        {
            "name": "Producteur",
            "value": ""
        },
        {
            "name": "Date de création",
            "value": "30/08/2023 18:50"
        },
        {
            "name": "Date de modification",
            "value": "15/09/2025 10:12"
        }
    ],
    "main_title": "Dernier samourai (Le)",
    "sub_title": "Blu-Ray",
    "thumbnail_big": "db/2153_video/thumbnail_big",
    "thumbnail_mini": "db/2153_video/thumbnail_small"
}
