{
    "fields": [
        {
            "name": "Titre",
            "value": "Tomb Raider : L'Ange des ténèbres"
        },
        {
            "name": "Console",
            "value": "PlayStation 2"
        },
        {
            "name": "Genre",
            "value": "Action - Aventure"
        },
        {
            "name": "Date de sortie",
            "value": "06/02/2004"
        },
        {
            "name": "Editeur",
            "value": "Square Enix"
        },
        {
            "name": "Date d'achat",
            "value": ""
        },
        {
            "name": "Nombre de joueurs",
            "value": ""
        },
        {
            "name": "Etat",
            "value": ""
        },
        {
            "name": "Classement",
            "value": "0 %"
        },
        {
            "name": "Langue(s) / Pays",
            "value": ""
        },
        {
            "name": "Code pegi",
            "value": ""
        },
        {
            "name": "Prix d'achat",
            "value": ""
        },
        {
            "name": "Prêt",
            "value": ""
        },
        {
            "name": "Import",
            "value": ""
        },
        {
            "name": "EAN",
            "value": "5032921017824"
        },
        {
            "name": "Prix actuel",
            "value": ""
        },
        {
            "name": "Mode en ligne",
            "value": ""
        },
        {
            "name": "Souhaité",
            "value": ""
        },
        {
            "name": "Histoire",
            "value": "Après une absence inhabituelle, Lara Croft effectue un fracassant come-back sur PlayStation 2 ! Avec Tomb Raider The Angel of Darkness, la plus célèbre des aventurières a visiblement décidé de changer quelques unes de ces habitudes. L'histoire débutera sous la pluie, à Paris où l'attend son mentor, l'auguste Werner von Croy. Pourtant, arrivée à sa demeure, Lara découvrira le corps inerte de l'explorateur. Immédiatement suspectée de meurtre, la belle devra alors se soustraire à une terrible traque tout en menant son enquête. Les visites du Louvre, des sombres catacombes, mais aussi de la baroque ville de Prague en Hongrie sont d'ores et déjà au programme de cet épisode pas comme les autres. En effet, outre l'ambiance plus oppressante et l'action décuplée, autre changement notable, Lara n'évolue désormais plus seule... mais par moment accompagnée par Kurtis Trent. Un personnage mystérieux et, par certains aspects, bien mystique. Plus mature et plus sexy que jamais, miss Croft ne s'était jamais montrée aussi en forme (s). Une véritable résurrection pour cette saga mythique. --Nobuo"
        },
        {
            "name": "Commentaires",
            "value": ""
        },
        {
            "name": "Notes personnelles",
            "value": ""
        },
        {
            "name": "Date de création",
            "value": "21/01/2018 00:16"
        },
        {
            "name": "Date de modification",
            "value": "06/06/2023 12:10"
        }
    ],
    "main_title": "PlayStation 2",
    "sub_title": "Tomb Raider : L'Ange des ténèbres",
    "thumbnail_big": "db/517_videogame/thumbnail_big",
    "thumbnail_mini": "db/517_videogame/thumbnail_small"
}
