{
    "fields": [
        {
            "name": "Titre",
            "value": "Coyote Girls"
        },
        {
            "name": "Réalisateur(s)",
            "value": "David McNally"
        },
        {
            "name": "Genre",
            "value": "Comedie Drame et emotion"
        },
        {
            "name": "Durée (min)",
            "value": ""
        },
        {
            "name": "Acteurs",
            "value": "Piper Perabo Adam Garcia Maria Bello Melanie Lynskey John Goodman"
        },
        {
            "name": "Date de sortie (DVD)",
            "value": "02/05/2001"
        },
        {
            "name": "Date d'achat",
            "value": ""
        },
        {
            "name": "Classement",
            "value": "0 %"
        },
        {
            "name": "Zone",
            "value": "2"
        },
        {
            "name": "Code pegi",
            "value": "Accord parental souhaite"
        },
        {
            "name": "Nombre de supports",
            "value": "1"
        },
        {
            "name": "Prix d'achat",
            "value": "0.00 €"
        },
        {
            "name": "Prêt",
            "value": ""
        },
        {
            "name": "Type de support",
            "value": "DVD"
        },
        {
            "name": "Etat",
            "value": ""
        },
        {
            "name": "Prix actuel",
            "value": ""
        },
        {
            "name": "Souhaité",
            "value": ""
        },
        {
            "name": "Synopsis",
            "value": "A 21 ans Violet Sanford eve de devenir diva et de connaitre la gloire. Elle quitte le foyer familial pour New York. De desillusions en echecs elle a de moins en moins confiance en elle et ses espoirs de reussite eclatante s'amenuisent chaque jour.Acculee elle accepte de travailler dans un bar country celebre pour ses serveuses aux allures provoquantes le Coyote Ugly. Dans cet univers d'amazones dirige par la seduisante Lil Violet acquiert un certain sens du spectacle et une vraie popularite.}"
        },
        {
            "name": "Commentaires",
            "value": ""
        },
        {
            "name": "Autres infos",
            "value": ""
        },
        {
            "name": "Studio d'enregistrement",
            "value": "Buena Vista Home Entertainement"
        },
        {
            "name": "Pays",
            "value": ""
        },
        {
            "name": "Langue(s)",
            "value": ""
        },
        {
            "name": "Sous-titres",
            "value": ""
        },
        {
            "name": "Son",
            "value": ""
        },
        {
            "name": "Ratio",
            "value": "1.33:1"
        },
        {
            "name": "EAN",
            "value": "3459379410052"
        },
        {
            "name": "Format",
            "value": "PAL"
        },
        {
            "name": "Visionné",
            "value": ""
        },
        {
            "name": "Producteur",
            "value": ""
        },
        {
            "name": "Date de création",
            "value": "30/12/2017 10:27"
        },
        {
            "name": "Date de modification",
            "value": "17/02/2022 20:15"
        }
    ],
    "main_title": "Coyote Girls",
    "sub_title": "DVD",
    "thumbnail_big": "db/969_video/thumbnail_big",
    "thumbnail_mini": "db/969_video/thumbnail_small"
}
