{
    "fields": [
        {
            "name": "Titre",
            "value": "Presque célèbre (4k) (Almost Famous)"
        },
        {
            "name": "Réalisateur(s)",
            "value": "Cameron Crowe"
        },
        {
            "name": "Genre",
            "value": "Comédie dramatique"
        },
        {
            "name": "Durée (min)",
            "value": "123"
        },
        {
            "name": "Acteurs",
            "value": "Billy Crudup, Frances McDormand, Kate Hudson, Jason Lee, Patrick Fugit, Philip Seymour Hoffman, Zooey Deschanel, Michael Angarano, Anna Paquin, Fairuza Balk, Noah Taylor, John Fedevich, Mark Kozelek, Philip Seymour Hoffman"
        },
        {
            "name": "Date de sortie (DVD)",
            "value": "21/03/2001"
        },
        {
            "name": "Date d'achat",
            "value": "04/09/2025"
        },
        {
            "name": "Classement",
            "value": "0 %"
        },
        {
            "name": "Zone",
            "value": "2"
        },
        {
            "name": "Code pegi",
            "value": ""
        },
        {
            "name": "Nombre de supports",
            "value": "1"
        },
        {
            "name": "Prix d'achat",
            "value": "16.80 €"
        },
        {
            "name": "Prêt",
            "value": ""
        },
        {
            "name": "Type de support",
            "value": "Blu-Ray"
        },
        {
            "name": "Etat",
            "value": "Neuf sous emballage"
        },
        {
            "name": "Prix actuel",
            "value": ""
        },
        {
            "name": "Souhaité",
            "value": ""
        },
        {
            "name": "Synopsis",
            "value": "Dans les années 70, William Miller, un adolescent de quinze ans, ne vit que pour la musique rock. Ce qu'il souhaite le plus au monde, c'est écrire des articles sur cette musique qu'il aime tant.\n\nIl envoie un essai au magazine Rolling Stone dans l'espoir de devenir journaliste. Son talent n'est pas passé inaperçu : on est prêt à l'envoyer suivre le groupe Stillwater en tournée afin qu'il fasse un reportage sur eux.\n\nLe rêve devient réalité ; malgré les objections d'Elaine, sa mère, William s'engage dans cette folle aventure.\n\nIl n'est toutefois pas facile de gagner la confiance des musiciens, surtout lorsqu'on est journaliste. William prouve rapidement aux membres de Stillwater qu'il est avant tout un admirateur inconditionnel de leur musique. Au cours de leur tournée, il abandonne peu à peu la passivité de son rôle d'observateur pour participer à la vie du groupe.\n"
        },
        {
            "name": "Commentaires",
            "value": ""
        },
        {
            "name": "Autres infos",
            "value": ""
        },
        {
            "name": "Studio d'enregistrement",
            "value": ""
        },
        {
            "name": "Pays",
            "value": ""
        },
        {
            "name": "Langue(s)",
            "value": ""
        },
        {
            "name": "Sous-titres",
            "value": ""
        },
        {
            "name": "Son",
            "value": ""
        },
        {
            "name": "Ratio",
            "value": ""
        },
        {
            "name": "EAN",
            "value": "3333298301984"
        },
        {
            "name": "Format",
            "value": ""
        },
        {
            "name": "Visionné",
            "value": ""
        },
        {
            "name": "Producteur",
            "value": ""
        },
        {
            "name": "Date de création",
            "value": "04/09/2025 20:50"
        },
        {
            "name": "Date de modification",
            "value": "04/09/2025 20:57"
        }
    ],
    "main_title": "Presque célèbre (4k) (Almost Famous)",
    "sub_title": "Blu-Ray",
    "thumbnail_big": "db/3553_video/thumbnail_big",
    "thumbnail_mini": "db/3553_video/thumbnail_small"
}
