{
    "fields": [
        {
            "name": "Titre",
            "value": "Les Rebelles de la forêt (Open Season)"
        },
        {
            "name": "Réalisateur(s)",
            "value": "Roger Allers"
        },
        {
            "name": "Genre",
            "value": "Aventure, Anime, Comédie"
        },
        {
            "name": "Durée (min)",
            "value": "90"
        },
        {
            "name": "Acteurs",
            "value": "Jill Culton, Anthony Stacchi"
        },
        {
            "name": "Date de sortie (DVD)",
            "value": "01/01/2005"
        },
        {
            "name": "Date d'achat",
            "value": "17/08/2024"
        },
        {
            "name": "Classement",
            "value": "0 %"
        },
        {
            "name": "Zone",
            "value": "2"
        },
        {
            "name": "Code pegi",
            "value": ""
        },
        {
            "name": "Nombre de supports",
            "value": "1"
        },
        {
            "name": "Prix d'achat",
            "value": "2.67 €"
        },
        {
            "name": "Prêt",
            "value": ""
        },
        {
            "name": "Type de support",
            "value": "Blu-Ray"
        },
        {
            "name": "Etat",
            "value": "Très bon"
        },
        {
            "name": "Prix actuel",
            "value": ""
        },
        {
            "name": "Souhaité",
            "value": ""
        },
        {
            "name": "Synopsis",
            "value": "Depuis la nuit des temps, l'homme a toujours régné sur la forêt, mais cette fois, les choses pourraient bien changer...\n\nDans la petite ville de Timberline, Boog, un ours apprivoisé et heureux de l'être, va voir sa paisible existence bouleversée par sa rencontre avec Elliot, un cerf sauvage aussi maigrichon que bavard.\n\nElliot arrive à convaincre Boog de quitter sa vie de rêve auprès de Beth, la ranger qui l'a élevé depuis qu'il est ourson, pour aller \"vivre en liberté dans la nature\"... Mais Boog ignore tout de la vie sauvage, et les choses vont vite déraper. Avec l'ouverture de la chasse et les chasseurs à leurs trousses, Elliot doit absolument aider Boog à réveiller ses instincts pour qu'avec l'aide des autres animaux de la forêt, ils aient une chance de contre-attaquer tous ensemble...\n"
        },
        {
            "name": "Commentaires",
            "value": ""
        },
        {
            "name": "Autres infos",
            "value": ""
        },
        {
            "name": "Studio d'enregistrement",
            "value": ""
        },
        {
            "name": "Pays",
            "value": ""
        },
        {
            "name": "Langue(s)",
            "value": ""
        },
        {
            "name": "Sous-titres",
            "value": ""
        },
        {
            "name": "Son",
            "value": ""
        },
        {
            "name": "Ratio",
            "value": ""
        },
        {
            "name": "EAN",
            "value": "3333299910888"
        },
        {
            "name": "Format",
            "value": ""
        },
        {
            "name": "Visionné",
            "value": ""
        },
        {
            "name": "Producteur",
            "value": ""
        },
        {
            "name": "Date de création",
            "value": "17/08/2024 21:45"
        },
        {
            "name": "Date de modification",
            "value": "17/08/2024 22:04"
        }
    ],
    "main_title": "Les Rebelles de la forêt (Open Season)",
    "sub_title": "Blu-Ray",
    "thumbnail_big": "db/2721_video/thumbnail_big",
    "thumbnail_mini": "db/2721_video/thumbnail_small"
}
