{
    "fields": [
        {
            "name": "Titre",
            "value": "Ballerina"
        },
        {
            "name": "Réalisateur(s)",
            "value": "Eric Summer"
        },
        {
            "name": "Genre",
            "value": "Anime9"
        },
        {
            "name": "Durée (min)",
            "value": "0"
        },
        {
            "name": "Acteurs",
            "value": "Éric Warin"
        },
        {
            "name": "Date de sortie (DVD)",
            "value": "14/12/2016"
        },
        {
            "name": "Date d'achat",
            "value": "27/09/2024"
        },
        {
            "name": "Classement",
            "value": "0 %"
        },
        {
            "name": "Zone",
            "value": "2"
        },
        {
            "name": "Code pegi",
            "value": ""
        },
        {
            "name": "Nombre de supports",
            "value": "1"
        },
        {
            "name": "Prix d'achat",
            "value": "2.99 €"
        },
        {
            "name": "Prêt",
            "value": ""
        },
        {
            "name": "Type de support",
            "value": "Blu-Ray"
        },
        {
            "name": "Etat",
            "value": "Excellent"
        },
        {
            "name": "Prix actuel",
            "value": ""
        },
        {
            "name": "Souhaité",
            "value": ""
        },
        {
            "name": "Synopsis",
            "value": "Félicie est une jeune orpheline bretonne qui n’a qu’une passion : la danse. Avec son meilleur ami Victor qui aimerait devenir un grand inventeur, ils mettent au point un plan rocambolesque pour s’échapper de l’orphelinat, direction Paris, ville lumière et sa Tour Eiffel en construction ! Félicie devra se battre comme jamais, se dépasser et apprendre de ses erreurs pour réaliser son rêve le plus fou : devenir danseuse étoile à l’Opéra de Paris…"
        },
        {
            "name": "Commentaires",
            "value": ""
        },
        {
            "name": "Autres infos",
            "value": ""
        },
        {
            "name": "Studio d'enregistrement",
            "value": ""
        },
        {
            "name": "Pays",
            "value": ""
        },
        {
            "name": "Langue(s)",
            "value": ""
        },
        {
            "name": "Sous-titres",
            "value": ""
        },
        {
            "name": "Son",
            "value": ""
        },
        {
            "name": "Ratio",
            "value": ""
        },
        {
            "name": "EAN",
            "value": "5412370000842"
        },
        {
            "name": "Format",
            "value": ""
        },
        {
            "name": "Visionné",
            "value": ""
        },
        {
            "name": "Producteur",
            "value": ""
        },
        {
            "name": "Date de création",
            "value": "27/09/2024 18:17"
        },
        {
            "name": "Date de modification",
            "value": "27/09/2024 18:20"
        }
    ],
    "main_title": "Ballerina",
    "sub_title": "Blu-Ray",
    "thumbnail_big": "db/2821_video/thumbnail_big",
    "thumbnail_mini": "db/2821_video/thumbnail_small"
}
