{
    "fields": [
        {
            "name": "Titre",
            "value": "Fabelmans (The)"
        },
        {
            "name": "Réalisateur(s)",
            "value": "Steven Spielberg"
        },
        {
            "name": "Genre",
            "value": "Biopic, Drame"
        },
        {
            "name": "Durée (min)",
            "value": "151"
        },
        {
            "name": "Acteurs",
            "value": "Michelle Williams, Paul Dano, Seth Rogen, Gabriel LaBelle, Mateo Zoryon Francis-DeFord, Keeley Karsten, Alina Brace, Julia Butters, Judd Hirsch"
        },
        {
            "name": "Date de sortie (DVD)",
            "value": "22/02/2023"
        },
        {
            "name": "Date d'achat",
            "value": "05/07/2023"
        },
        {
            "name": "Classement",
            "value": "0 %"
        },
        {
            "name": "Zone",
            "value": "2"
        },
        {
            "name": "Code pegi",
            "value": ""
        },
        {
            "name": "Nombre de supports",
            "value": "1"
        },
        {
            "name": "Prix d'achat",
            "value": ""
        },
        {
            "name": "Prêt",
            "value": ""
        },
        {
            "name": "Type de support",
            "value": "Blu-Ray"
        },
        {
            "name": "Etat",
            "value": "Neuf sous emballage"
        },
        {
            "name": "Prix actuel",
            "value": ""
        },
        {
            "name": "Souhaité",
            "value": ""
        },
        {
            "name": "Synopsis",
            "value": "Portrait profondément intime d’une enfance américaine au XXème siècle, The Fabelmans de Steven Spielberg nous plonge dans l’histoire familiale du cinéaste qui a façonné sa vie personnelle et professionnelle. À partir du récit initiatique d’un jeune homme solitaire qui aspire à réaliser ses rêves, le film explore les relations amoureuses, l’ambition artistique, le sacrifice et les moments de lucidité qui nous permettent d’avoir un regard sincère et tendre sur nous-mêmes et nos parents.\n\nPassionné de cinéma, Sammy Fabelman passe son temps à filmer sa famille. S’il est encouragé dans cette voie par sa mère Mitzi, dotée d’un tempérament artistique, son père Burt, scientifique accompli, considère que sa passion est surtout un passe-temps. Au fil des années, Sammy, à force de pointer sa caméra sur ses parents et ses sœurs, est devenu le documentariste de l’histoire familiale ! Il réalise même de petits films amateurs de plus en plus sophistiqués, interprétés par ses amis et ses sœurs. Mais lorsque ses parents décident de déménager dans l’ouest du pays, il découvre une réalité bouleversante sur sa mère qui bouscule ses rapports avec elle et fait basculer son avenir et celui de ses proches. "
        },
        {
            "name": "Commentaires",
            "value": "A vendre"
        },
        {
            "name": "Autres infos",
            "value": ""
        },
        {
            "name": "Studio d'enregistrement",
            "value": ""
        },
        {
            "name": "Pays",
            "value": ""
        },
        {
            "name": "Langue(s)",
            "value": ""
        },
        {
            "name": "Sous-titres",
            "value": ""
        },
        {
            "name": "Son",
            "value": ""
        },
        {
            "name": "Ratio",
            "value": ""
        },
        {
            "name": "EAN",
            "value": "8713045251574"
        },
        {
            "name": "Format",
            "value": ""
        },
        {
            "name": "Visionné",
            "value": "Oui"
        },
        {
            "name": "Producteur",
            "value": ""
        },
        {
            "name": "Date de création",
            "value": "05/07/2023 22:44"
        },
        {
            "name": "Date de modification",
            "value": "27/01/2024 16:28"
        }
    ],
    "main_title": "Fabelmans (The)",
    "sub_title": "Blu-Ray",
    "thumbnail_big": "db/2078_video/thumbnail_big",
    "thumbnail_mini": "db/2078_video/thumbnail_small"
}
