{
    "fields": [
        {
            "name": "Titre",
            "value": "Albator - L'integrale"
        },
        {
            "name": "Réalisateur(s)",
            "value": "Rin Taro Rintaro"
        },
        {
            "name": "Genre",
            "value": "Anime"
        },
        {
            "name": "Durée (min)",
            "value": ""
        },
        {
            "name": "Acteurs",
            "value": ""
        },
        {
            "name": "Date de sortie (DVD)",
            "value": "02/10/2012"
        },
        {
            "name": "Date d'achat",
            "value": ""
        },
        {
            "name": "Classement",
            "value": "0 %"
        },
        {
            "name": "Zone",
            "value": "2"
        },
        {
            "name": "Code pegi",
            "value": "Tous publics"
        },
        {
            "name": "Nombre de supports",
            "value": "6"
        },
        {
            "name": "Prix d'achat",
            "value": "0.00 €"
        },
        {
            "name": "Prêt",
            "value": ""
        },
        {
            "name": "Type de support",
            "value": "DVD"
        },
        {
            "name": "Etat",
            "value": ""
        },
        {
            "name": "Prix actuel",
            "value": ""
        },
        {
            "name": "Souhaité",
            "value": ""
        },
        {
            "name": "Synopsis",
            "value": "En l'an de grace 2980 les Terriens nagent dans l'opulence. Ils ont envoye des robots qui exploitent les ressources des autres planetes et ces richesses sont distribuees gratuitement a la population. Cette situation cache cependant une triste realite : l'Humanite a renonce a sa liberte. Les hommes vivent sous le joug d'une classe politique faineante et lache qui les asservit par le biais de la television. Un homme a refuse cette vie oisive et beate. Il s'agit d'Albator le corsaire de l'espace. Declare hors-la-loi il continue pourtant de proteger la Terre. Lui et son equipage sont les seuls encore assez lucides pour comprendre le danger qui menace. Ils vont se dresser contre les terribles Sylvidres un peuple qui cherche a conquerir la planete bleue...}"
        },
        {
            "name": "Commentaires",
            "value": ""
        },
        {
            "name": "Autres infos",
            "value": ""
        },
        {
            "name": "Studio d'enregistrement",
            "value": "TF1 Video"
        },
        {
            "name": "Pays",
            "value": ""
        },
        {
            "name": "Langue(s)",
            "value": ""
        },
        {
            "name": "Sous-titres",
            "value": ""
        },
        {
            "name": "Son",
            "value": ""
        },
        {
            "name": "Ratio",
            "value": "1.33:1"
        },
        {
            "name": "EAN",
            "value": "3384442251631"
        },
        {
            "name": "Format",
            "value": "PAL"
        },
        {
            "name": "Visionné",
            "value": ""
        },
        {
            "name": "Producteur",
            "value": ""
        },
        {
            "name": "Date de création",
            "value": "30/12/2017 10:27"
        },
        {
            "name": "Date de modification",
            "value": "17/02/2022 20:15"
        }
    ],
    "main_title": "Albator - L'integrale",
    "sub_title": "DVD",
    "thumbnail_big": "db/458_video/thumbnail_big",
    "thumbnail_mini": "db/458_video/thumbnail_small"
}
